<joblist>
  <job>
    <defaultTab>nodes</defaultTab>
    <description></description>
    <executionEnabled>true</executionEnabled>
    <id>a41cb39d-6fca-49c2-80e8-861fac74df72</id>
    <loglevel>INFO</loglevel>
    <name>job163</name>
    <nodeFilterEditable>false</nodeFilterEditable>
    <plugins />
    <scheduleEnabled>true</scheduleEnabled>
    <sequence keepgoing='false' strategy='node-first'>
      <command>
        <exec>uname</exec>
      </command>
    </sequence>
    <uuid>a41cb39d-6fca-49c2-80e8-861fac74df72</uuid>
  </job>
</joblist>
