<joblist>
  <job>
    <defaultTab>nodes</defaultTab>
    <description></description>
    <executionEnabled>true</executionEnabled>
    <id>852f0af7-2d7b-48d1-b91a-b859c848306c</id>
    <loglevel>INFO</loglevel>
    <name>job235</name>
    <nodeFilterEditable>false</nodeFilterEditable>
    <plugins />
    <scheduleEnabled>true</scheduleEnabled>
    <sequence keepgoing='false' strategy='node-first'>
      <command>
        <exec>uname</exec>
      </command>
    </sequence>
    <uuid>852f0af7-2d7b-48d1-b91a-b859c848306c</uuid>
  </job>
</joblist>
